<?xml version="1.0" encoding="utf-8"?>
<!DOCTYPE hibernate-mapping PUBLIC "-//Hibernate/Hibernate Mapping DTD 3.0//EN"
"http://hibernate.sourceforge.net/hibernate-mapping-3.0.dtd">
<!-- 
    Mapping file autogenerated by MyEclipse Persistence Tools
-->
<hibernate-mapping>
    <class name="com.student.bean.UserMenu" table="user_menu" catalog="db_student">
        <id name="menuSeq" type="java.lang.Integer">
            <column name="MenuSeq" />
            <generator class="native" />
        </id>
        <property name="menuName" type="java.lang.String">
            <column name="MenuName" length="50" />
        </property>
        <property name="fmenuSeq" type="java.lang.Integer">
            <column name="FmenuSeq" />
        </property>
        <property name="menuLayer" type="java.lang.Integer">
            <column name="MenuLayer" />
        </property>
        <property name="menuPath" type="java.lang.String">
            <column name="MenuPath" length="100" />
        </property>
    </class>
</hibernate-mapping>
